deepexplain/__init__.py
deepexplain/tensorflow/__init__.py
deepexplain/tensorflow/methods.py
deepexplain/tensorflow/utils.py
deepexplain/tests/__init__.py
deepexplain/tests/test_tensorflow.py
siVAE/FeatureImportance.py
siVAE/__init__.py
siVAE/analysis.py
siVAE/classifier.py
siVAE/plot_gmm.py
siVAE/util.py
siVAE/data/__init__.py
siVAE/data/data_handler.py
siVAE/data/data_handler_old.py
siVAE/data/tfdata.py
siVAE/data/tfrecord.py
siVAE/model/VAE.py
siVAE/model/__init__.py
siVAE/model/analysis.py
siVAE/model/layer.py
siVAE/model/plot.py
siVAE/model/run_model.py
siVAE/model/siVAE.py
siVAE/model/siVAE2.py
siVAE/model/util.py
tensorflow_forward_ad/__init__.py
tensorflow_forward_ad/bfs.py
tensorflow_forward_ad/bfs_tests.py
tensorflow_forward_ad/fwgrad.py
tensorflow_forward_ad/fwgrad_tests.py
tensorflow_forward_ad/graph.py
tensorflow_forward_ad/logger.py
tensorflow_forward_ad/maxpool_gradgrad.py
tensorflow_forward_ad/maxpool_gradgrad_tests.py
tensorflow_forward_ad/second_order.py
tensorflow_forward_ad/second_order_tests.py
tensorflow_forward_ad/setup_cbfs.py
siVAE-0.3.dist-info/LICENSE.md
siVAE-0.3.dist-info/LICENSE.txt
siVAE-0.3.dist-info/METADATA
siVAE-0.3.dist-info/WHEEL
siVAE-0.3.dist-info/top_level.txt
siVAE-0.3.dist-info/RECORD
